{
  "project_info": {
    "project_number": "893370806643",
    "firebase_url": "https://eventreporter-af70b.firebaseio.com",
    "project_id": "eventreporter-af70b",
    "storage_bucket": "eventreporter-af70b.appspot.com"
  },
  "client": [
    {
      "client_info": {
        "mobilesdk_app_id": "1:893370806643:android:42e76512306dcb38",
        "android_client_info": {
          "package_name": "com.laioffer.eventreporter"
        }
      },
      "oauth_client": [
        {
          "client_id": "893370806643-c05ru15kfip0lno2ra465tm4u0d5rn39.apps.googleusercontent.com",
          "client_type": 1,
          "android_info": {
            "package_name": "com.laioffer.eventreporter",
            "certificate_hash": "1fae8d9152669c2534a86f1b25f99378cb02f01e"
          }
        },
        {
          "client_id": "893370806643-2c6r5lkrt2dsd0h7ma5bvqc1o1ff3nqd.apps.googleusercontent.com",
          "client_type": 3
        }
      ],
      "api_key": [
        {
          "current_key": "AIzaSyC-KwrurCkYOuXKrTeb7Pv-EdL6sGplBdo"
        }
      ],
      "services": {
        "analytics_service": {
          "status": 1
        },
        "appinvite_service": {
          "status": 2,
          "other_platform_oauth_client": [
            {
              "client_id": "893370806643-2c6r5lkrt2dsd0h7ma5bvqc1o1ff3nqd.apps.googleusercontent.com",
              "client_type": 3
            }
          ]
        },
        "ads_service": {
          "status": 2
        }
      }
    }
  ],
  "configuration_version": "1"
}